doc_loader/__init__.py
doc_loader/doc_loader.py
doc_loader/errors.py
doc_loader/page_counter.py
doc_loader/pdf_extract.py
doc_loader/readers.py
doc_loader/types.py
doc_loader/utils.py
doc_loader-0.1.3.dist-info/LICENSE
doc_loader-0.1.3.dist-info/METADATA
doc_loader-0.1.3.dist-info/WHEEL
doc_loader-0.1.3.dist-info/top_level.txt
doc_loader-0.1.3.dist-info/zip-safe
doc_loader-0.1.3.dist-info/RECORD
