Metadata-Version: 2.1
Name: doc-loader
Version: 0.1.3
Summary: Given werkzeug.FileStorage, fastapi.UploadFile or str file path as input it converts any image files(.pdf, .jpg, .png, .tiff) into list of PIL or numpy objects
Home-page: https://github.com/CapgeminiInventIDE/doc_loader
Author: Capgemini Invent IDE
License: UNKNOWN
Keywords: image loading,document handling,PIL wrapper
Platform: UNKNOWN
Classifier: Programming Language :: Python :: 3
Classifier: License :: OSI Approved :: Mozilla Public License 2.0 (MPL 2.0)
Classifier: Operating System :: OS Independent
Requires-Python: >=3.6
Requires-Dist: Pillow
Requires-Dist: pdf2image
Requires-Dist: numpy
Provides-Extra: pdf_text_extract
Requires-Dist: PyMuPDF ; extra == 'pdf_text_extract'
